Magmar/__init__.py
Magmar/utils.py
magmar-0.3.0.dist-info/METADATA
magmar-0.3.0.dist-info/WHEEL
magmar-0.3.0.dist-info/top_level.txt
magmar-0.3.0.dist-info/RECORD
